listpick/__init__.py
listpick/__main__.py
listpick/listpick_app.py
listpick/pane/__init__.py
listpick/pane/get_data.py
listpick/pane/left_pane_functions.py
listpick/pane/pane_functions.py
listpick/pane/pane_functions_1.py
listpick/pane/pane_utils.py
listpick/ui/__init__.py
listpick/ui/build_help.py
listpick/ui/draw_screen.py
listpick/ui/footer.py
listpick/ui/help_screen.py
listpick/ui/input_field.py
listpick/ui/keys.py
listpick/ui/picker_colours.py
listpick/utils/__init__.py
listpick/utils/clipboard_operations.py
listpick/utils/config.py
listpick/utils/dump.py
listpick/utils/filtering.py
listpick/utils/generate_data.py
listpick/utils/generate_data_multiprocessing.py
listpick/utils/generate_data_multithreaded.py
listpick/utils/generate_data_utils.py
listpick/utils/graphing.py
listpick/utils/keycodes.py
listpick/utils/options_selectors.py
listpick/utils/paste_operations.py
listpick/utils/picker_log.py
listpick/utils/picker_state.py
listpick/utils/search_and_filter_utils.py
listpick/utils/searching.py
listpick/utils/sorting.py
listpick/utils/table_to_list_of_lists.py
listpick/utils/user_input.py
listpick/utils/utils.py
listpick-0.1.18.0.dist-info/licenses/LICENSE.txt
listpick-0.1.18.0.dist-info/METADATA
listpick-0.1.18.0.dist-info/WHEEL
listpick-0.1.18.0.dist-info/entry_points.txt
listpick-0.1.18.0.dist-info/top_level.txt
listpick-0.1.18.0.dist-info/RECORD
