Metadata-Version: 2.4
Name: listpick
Version: 0.1.18.0
Summary: Listpick is a powerful TUI data tool for creating TUI apps or viewing/comparing tabulated data.
Home-page: https://github.com/grimandgreedy/listpick
Author: Grim
Author-email: grimandgreedy@protonmail.com
Project-URL: Bug Tracker, https://github.com/grimandgreedy/listpick/issues
Classifier: Programming Language :: Python :: 3
Classifier: License :: OSI Approved :: MIT License
Classifier: Operating System :: Unix
Requires-Python: >=3.9
License-File: LICENSE.txt
Requires-Dist: wcwidth
Requires-Dist: pyperclip
Requires-Dist: toml
Requires-Dist: dill
Provides-Extra: full
Requires-Dist: dill; extra == "full"
Requires-Dist: wcwidth; extra == "full"
Requires-Dist: ipython; extra == "full"
Requires-Dist: msgpack; extra == "full"
Requires-Dist: openpyxl; extra == "full"
Requires-Dist: pandas; extra == "full"
Requires-Dist: pyperclip; extra == "full"
Requires-Dist: toml; extra == "full"
Requires-Dist: traitlets; extra == "full"
Requires-Dist: odfpy; extra == "full"
Requires-Dist: plotille; extra == "full"
Dynamic: author
Dynamic: author-email
Dynamic: classifier
Dynamic: description
Dynamic: description-content-type
Dynamic: home-page
Dynamic: license-file
Dynamic: project-url
Dynamic: provides-extra
Dynamic: requires-dist
Dynamic: requires-python
Dynamic: summary
